<?xml version="1.0" encoding="UTF-8" ?>
<pageDefinition xmlns="http://xmlns.oracle.com/adfm/uimodel" version="12.2.1.9.14" id="workerTemplatePageDef"
                Package="web.template2">
  <parameters/>
  <executables>
    <variableIterator id="variables"/>
    <iterator Binds="WorkerDraftView1" RangeSize="25" DataControl="AppModuleDataControl" id="WorkerDraftView1Iterator"/>
    <searchRegion Binds="WorkerDraftView1Iterator" Criteria=""
                  Customizer="oracle.jbo.uicli.binding.JUSearchBindingCustomizer" id="WorkerDraftView1Query"/>
  </executables>
  <bindings>
    <action id="Commit" RequiresUpdateModel="true" Action="commitTransaction" DataControl="AppModuleDataControl"/>
    <tree IterBinding="WorkerDraftView1Iterator" id="WorkerDraftView1">
      <nodeDefinition DefName="model.WorkerDraftView" Name="WorkerDraftView10">
        <AttrNames>
          <Item Value="SerialNumber"/>
          <Item Value="Qid"/>
          <Item Value="Name"/>
          <Item Value="NationalityCode"/>
          <Item Value="Gender"/>
          <Item Value="SocialStatus"/>
          <Item Value="SpouseQid"/>
          <Item Value="BirthDate"/>
          <Item Value="HiringDate"/>
          <Item Value="JobNumber"/>
          <Item Value="JobName"/>
          <Item Value="ContractType"/>
          <Item Value="EducationalLevel"/>
          <Item Value="Specialization"/>
          <Item Value="BasicSalary"/>
          <Item Value="SocialAllowance"/>
          <Item Value="TransportAllowance"/>
          <Item Value="WorkNatureAllowance"/>
          <Item Value="HousingAllowance"/>
          <Item Value="OtherAllowance"/>
          <Item Value="TotalMonthlySalary"/>
          <Item Value="HousingType"/>
          <Item Value="AdditionalNotes"/>
        </AttrNames>
      </nodeDefinition>
    </tree>
    <tree IterBinding="WorkerDraftView1Iterator" id="WorkerDraftView11">
      <nodeDefinition DefName="view.WorkerDraftView" Name="WorkerDraftView110">
        <AttrNames>
          <Item Value="SerialNumber"/>
          <Item Value="Qid"/>
          <Item Value="Name"/>
          <Item Value="NationalityCode"/>
          <Item Value="Gender"/>
          <Item Value="SocialStatus"/>
          <Item Value="SpouseQid"/>
          <Item Value="BirthDate"/>
          <Item Value="HiringDate"/>
          <Item Value="JobNumber"/>
          <Item Value="JobName"/>
          <Item Value="ContractType"/>
          <Item Value="EducationalLevel"/>
          <Item Value="Specialization"/>
          <Item Value="BasicSalary"/>
          <Item Value="SocialAllowance"/>
          <Item Value="TransportAllowance"/>
          <Item Value="WorkNatureAllowance"/>
          <Item Value="HousingAllowance"/>
          <Item Value="OtherAllowance"/>
          <Item Value="TotalMonthlySalary"/>
          <Item Value="HousingType"/>
          <Item Value="AdditionalNotes"/>
        </AttrNames>
      </nodeDefinition>
    </tree>
  </bindings>
</pageDefinition>
